[
    {
        "MajorName": "Accounting (CB)",
        "Bachelors": true,
        "Masters": true,
        "Doctorate": false,
        "Other": false
    },{
    "MajorName": "African and American Diaspora Studies (AS)",
        "Bachelors": true,
        "Masters": false,
        "Doctorate": false,
        "Other": false
    },{
    "MajorName": "Agricultural Business (AG)",
        "Bachelors": true,
        "Masters": false,
        "Doctorate": false,
        "Other": false
    },{
    "MajorName": "Agricultural Communications (AG)",
        "Bachelors": true,
        "Masters": false,
        "Doctorate": false,
        "Other": false
    },{
    "MajorName": "Agriculture and Applied Economics (AG)",
        "Bachelors": false,
        "Masters": true,
        "Doctorate": false,
        "Other": false
    },{
    "MajorName": "Agricultural Economics/Water Resources (AG)",
        "Bachelors": false,
        "Masters": true,
        "Doctorate": false,
        "Other": false
    },{
    "MajorName": "Agricultural Education (ED)",
        "Bachelors": true,
        "Masters": false,
        "Doctorate": false,
        "Other": false
    },{
    "MajorName": "Agronomy (AG)",
        "Bachelors": false,
        "Masters": true,
        "Doctorate": true,
        "Other": false
    },{
    "MajorName": "African American and Diaspora Studies (AS)",
        "Bachelors": true,
        "Masters": false,
        "Doctorate": false,
        "Other": false
    },{
    "MajorName": "American Indian Studies (AS)",
        "Bachelors": true,
        "Masters": false,
        "Doctorate": false,
        "Other": false
    },{
    "MajorName": "American Studies (AS)",
        "Bachelors": true,
        "Masters": true,
        "Doctorate": false,
        "Other": false
    },{
    "MajorName": "Animal and Veterinary Sciences (AG)",
        "Bachelors": true,
        "Masters": true,
        "Doctorate": true,
        "Other": false
    },{
    "MajorName": "Anthropology (AS)",
        "Bachelors": true,
        "Masters": true,
        "Doctorate": true,
        "Other": false
    },{
    "MajorName": "Architectural Engineering (EN)",
        "Bachelors": true,
        "Masters": true,
        "Doctorate": false,
        "Other": false
    },{
    "MajorName": "Art (AS)",
        "Bachelors": true,
        "Masters": false,
        "Doctorate": false,
        "Other": false
    },{
    "MajorName": "Art History (AS)",
        "Bachelors": true,
        "Masters": false,
        "Doctorate": false,
        "Other": false
    },{
    "MajorName": "Astronomy/Astrophysics (AS)",
        "Bachelors": true,
        "Masters": false,
        "Doctorate": false,
        "Other": false
    },{
    "MajorName": "Atmospheric Science (EN)",
        "Bachelors": false,
        "Masters": true,
        "Doctorate": true,
        "Other": false
    },{
    "MajorName": "Biology (AS)",
        "Bachelors": true,
        "Masters": false,
        "Doctorate": false,
        "Other": false
    },{
    "MajorName": "Biomedical Sciences (AG, EN, AS, HS)",
        "Bachelors": false,
        "Masters": false,
        "Doctorate": true,
        "Other": false
    },{
    "MajorName": "Botany (AS)",
        "Bachelors": true,
        "Masters": true,
        "Doctorate": true,
        "Other": false
    },{
    "MajorName": "Botany/ Water Resources (AS)",
        "Bachelors": false,
        "Masters": true,
        "Doctorate": false,
        "Other": false
    },{
    "MajorName": "Business Administration (CB)",
        "Bachelors": true,
        "Masters": true,
        "Doctorate": false,
        "Other": false
    },{
    "MajorName": "Business Economics (CB)",
        "Bachelors": true,
        "Masters": false,
        "Doctorate": false,
        "Other": false
    },{
    "MajorName": "Chemical Engineering (EN)",
        "Bachelors": true,
        "Masters": true,
        "Doctorate": true,
        "Other": false
    },{
    "MajorName": "Chemistry (AS)",
        "Bachelors": true,
        "Masters": true,
        "Doctorate": true,
        "Other": false
    },{
    "MajorName": "Chemistry (ACS Approved) (AS)",
        "Bachelors": true,
        "Masters": false,
        "Doctorate": false,
        "Other": false
    },{
    "MajorName": "Civil Engineering (EN)",
        "Bachelors": true,
        "Masters": true,
        "Doctorate": true,
        "Other": false
    },{
    "MajorName": "Civil Engineering/Water Resources (EN)",
        "Bachelors": false,
        "Masters": true,
        "Doctorate": false,
        "Other": false
    },{
    "MajorName": "Communication (AS)",
        "Bachelors": true,
        "Masters": true,
        "Doctorate": false,
        "Other": false
    },{
    "MajorName": "Computer Engineering (EN)",
        "Bachelors": true,
        "Masters": false,
        "Doctorate": false,
        "Other": false
    },{
    "MajorName": "Computer Science (EN)",
        "Bachelors": true,
        "Masters": true,
        "Doctorate": true,
        "Other": false
    },{
    "MajorName": "Counseling (ED)",
        "Bachelors": false,
        "Masters": true,
        "Doctorate": false,
        "Other": false
    },{
    "MajorName": "Counselor Education and Supervision (ED)",
        "Bachelors": false,
        "Masters": false,
        "Doctorate": true,
        "Other": false
    },{
    "MajorName": "Creative Writing (AS)",
        "Bachelors": false,
        "Masters": true,
        "Doctorate": false,
        "Other": false
    },{
    "MajorName": "Criminal Justice (AS)",
        "Bachelors": true,
        "Masters": false,
        "Doctorate": false,
        "Other": false
    },{
    "MajorName": "Curriculum and Instruction (ED)",
        "Bachelors": true,
        "Masters": false,
        "Doctorate": false,
        "Other": false
    },{
    "MajorName": "Dental Hygiene (HS) (at Sheridan College)",
        "Bachelors": true,
        "Masters": false,
        "Doctorate": false,
        "Other": false
    },{
    "MajorName": "Ecology (UW)",
        "Bachelors": false,
        "Masters": false,
        "Doctorate": true,
        "Other": false
    },{
    "MajorName": "Economics (CB)",
        "Bachelors": true,
        "Masters": true,
        "Doctorate": true,
        "Other": false
    },{
    "MajorName": "Economics and Finance (CB)",
        "Bachelors": false,
        "Masters": true,
        "Doctorate": false,
        "Other": false
    },{
    "MajorName": "Economics/Water Resources (CB)",
        "Bachelors": false,
        "Masters": true,
        "Doctorate": false,
        "Other": false
    },{
    "MajorName": "Education (ED)",
        "Bachelors": false,
        "Masters": true,
        "Doctorate": true,
        "Other": true
    },{
    "MajorName": "Education Specialist (ED)",
        "Bachelors": false,
        "Masters": false,
        "Doctorate": false,
        "Other": true
    },{
    "MajorName": "Electrical Engineering (EN)",
        "Bachelors": true,
        "Masters": true,
        "Doctorate": true,
        "Other": false
    },{
    "MajorName": "Elementary Education (ED)",
        "Bachelors": true,
        "Masters": false,
        "Doctorate": false,
        "Other": false
    },{
    "MajorName": "Energy management (CB)",
        "Bachelors": false,
        "Masters": true,
        "Doctorate": false,
        "Other": false
    },{
    "MajorName": "Energy Resource Management and Development (SER)",
        "Bachelors": true,
        "Masters": false,
        "Doctorate": false,
        "Other": false
    },{
    "MajorName": "Energy Systems Engineering",
        "Bachelors": true,
        "Masters": false,
        "Doctorate": false,
        "Other": false
    },{
    "MajorName": "English (AS)",
        "Bachelors": true,
        "Masters": true,
        "Doctorate": false,
        "Other": false
    },{
    "MajorName": "Entomology (AG)",
        "Bachelors": false,
        "Masters": true,
        "Doctorate": true,
        "Other": false
    },{
    "MajorName": "Environment and Natural Resources (affiliated major) (HN)",
        "Bachelors": true,
        "Masters": false,
        "Doctorate": false,
        "Other": false
    },{
    "MajorName": "Environmental Engineering (EN)",
        "Bachelors": false,
        "Masters": true,
        "Doctorate": false,
        "Other": false
    },{
    "MajorName": "Environmental Geology/Geohydrology (AS)",
        "Bachelors": true,
        "Masters": false,
        "Doctorate": false,
        "Other": false
    },{
    "MajorName": "Environmental systems science (HN)",
        "Bachelors": true,
        "Masters": false,
        "Doctorate": false,
        "Other": false
    },{
    "MajorName": "Family and Consumer Sciences (AG)",
        "Bachelors": true,
        "Masters": true,
        "Doctorate": false,
        "Other": false
    },{
    "MajorName": "Finance (CB)",
        "Bachelors": true,
        "Masters": true,
        "Doctorate": false,
        "Other": false
    },{
    "MajorName": "Food Science and Human Nutrition (AG)",
        "Bachelors": false,
        "Masters": true,
        "Doctorate": false,
        "Other": false
    },{
    "MajorName": "French (AS)",
        "Bachelors": true,
        "Masters": false,
        "Doctorate": false,
        "Other": false
    },{
    "MajorName": "Gender and Women's Studies (AS)",
        "Bachelors": true,
        "Masters": false,
        "Doctorate": false,
        "Other": false
    },{
    "MajorName": "Geography (AS) *under review",
        "Bachelors": true,
        "Masters": true,
        "Doctorate": false,
        "Other": false
    },{
    "MajorName": "Geography/Water Resources (AS) *under review",
        "Bachelors": false,
        "Masters": true,
        "Doctorate": false,
        "Other": false
    },{
    "MajorName": "Geology (AS)",
        "Bachelors": true,
        "Masters": true,
        "Doctorate": true,
        "Other": false
    },{
    "MajorName": "Geology and Earth Sciences (AS)",
        "Bachelors": true,
        "Masters": false,
        "Doctorate": false,
        "Other": false
    },{
    "MajorName": "Geology/Water Resources (AS)",
        "Bachelors": false,
        "Masters": true,
        "Doctorate": false,
        "Other": false
    },{
    "MajorName": "Geophysics (AS)",
        "Bachelors": false,
        "Masters": true,
        "Doctorate": true,
        "Other": false
    },{
    "MajorName": "German (AS)",
        "Bachelors": true,
        "Masters": false,
        "Doctorate": false,
        "Other": false
    },{
    "MajorName": "Health services administration (HS)",
        "Bachelors": false,
        "Masters": true,
        "Doctorate": false,
        "Other": false
    },{
    "MajorName": "History (AS)",
        "Bachelors": true,
        "Masters": true,
        "Doctorate": false,
        "Other": false
    },{
    "MajorName": "Hydrological Sciences (UW)",
        "Bachelors": false,
        "Masters": false,
        "Doctorate": true,
        "Other": false
    },{
    "MajorName": "International Studies (AS)",
        "Bachelors": true,
        "Masters": true,
        "Doctorate": false,
        "Other": false
    },{
    "MajorName": "Journalism (AS)",
        "Bachelors": true,
        "Masters": false,
        "Doctorate": false,
        "Other": false
    },{
    "MajorName": "Juris Doctor (LAW)",
        "Bachelors": false,
        "Masters": false,
        "Doctorate": false,
        "Other": true
    },{
    "MajorName": "Kinesiology and Health (HS)",
        "Bachelors": false,
        "Masters": true,
        "Doctorate": false,
        "Other": false
    },{
    "MajorName": "Kinesiology and Health Promotion (HS)",
        "Bachelors": true,
        "Masters": false,
        "Doctorate": false,
        "Other": false
    },{
    "MajorName": "Management (CB)",
        "Bachelors": true,
        "Masters": false,
        "Doctorate": false,
        "Other": false
    },{
    "MajorName": "Management and Marketing (CB)",
        "Bachelors": false,
        "Masters": false,
        "Doctorate": true,
        "Other": false
    },{
    "MajorName": "Marketing (CB)",
        "Bachelors": true,
        "Masters": false,
        "Doctorate": false,
        "Other": false
    },{
    "MajorName": "Mathematics (AS)",
        "Bachelors": true,
        "Masters": true,
        "Doctorate": true,
        "Other": false
    },{
    "MajorName": "Mechanical Engineering (EN)",
        "Bachelors": true,
        "Masters": true,
        "Doctorate": true,
        "Other": false
    },{
    "MajorName": "Medical Laboratory Science (HS) (through UW-Casper)",
        "Bachelors": true,
        "Masters": false,
        "Doctorate": false,
        "Other": false
    },{
    "MajorName": "Microbiology (AG)",
        "Bachelors": true,
        "Masters": false,
        "Doctorate": false,
        "Other": false
    },{
    "MajorName": "Molecular Biology (AG)",
        "Bachelors": true,
        "Masters": true,
        "Doctorate": true,
        "Other": false
    },{
    "MajorName": "Molecular and Cellular Life Sciences (UW)",
        "Bachelors": false,
        "Masters": false,
        "Doctorate": true,
        "Other": false
    },{
    "MajorName": "Music (AS)",
        "Bachelors": true,
        "Masters": false,
        "Doctorate": false,
        "Other": false
    },{
    "MajorName": "Music Education (AS)",
        "Bachelors": true,
        "Masters": true,
        "Doctorate": false,
        "Other": false
    },{
    "MajorName": "Music Performance (AS)",
        "Bachelors": true,
        "Masters": true,
        "Doctorate": false,
        "Other": true
    },{
    "MajorName": "Natural Science (Inter)",
        "Bachelors": false,
        "Masters": true,
        "Doctorate": false,
        "Other": false
    },{
    "MajorName": "Neuroscience (AS and UW)",
        "Bachelors": false,
        "Masters": false,
        "Doctorate": true,
        "Other": false
    },{
    "MajorName": "Nursing (HS)",
        "Bachelors": true,
        "Masters": true,
        "Doctorate": false,
        "Other": false
    },{
    "MajorName": "Nursing Practice (HS)",
        "Bachelors": false,
        "Masters": false,
        "Doctorate": true,
        "Other": false
    },{
    "MajorName": "Organizational Leadership (Bachelor of Applied Science) (AG)",
        "Bachelors": false,
        "Masters": false,
        "Doctorate": false,
        "Other": true
    },{
    "MajorName": "Petroleum Engineering (EN)",
        "Bachelors": true,
        "Masters": true,
        "Doctorate": true,
        "Other": false
    },{
    "MajorName": "Pharmacy (Professional) (HS)",
        "Bachelors": false,
        "Masters": false,
        "Doctorate": false,
        "Other": true
    },{
    "MajorName": "Philosophy (AS)",
        "Bachelors": true,
        "Masters": true,
        "Doctorate": false,
        "Other": false
    },{
    "MajorName": "Physical Education Teaching (HS)",
        "Bachelors": true,
        "Masters": false,
        "Doctorate": false,
        "Other": false
    },{
    "MajorName": "Physics (AS)",
        "Bachelors": true,
        "Masters": true,
        "Doctorate": true,
        "Other": false
    },{
    "MajorName": "Physiology (AS)",
        "Bachelors": true,
        "Masters": false,
        "Doctorate": false,
        "Other": false
    },{
    "MajorName": "Planning (Community and Regional) (AS)",
        "Bachelors": false,
        "Masters": true,
        "Doctorate": false,
        "Other": false
    },{
    "MajorName": "Plant Sciences (AG)",
        "Bachelors": false,
        "Masters": true,
        "Doctorate": true,
        "Other": false
    },{
    "MajorName": "Political Science (AS)",
        "Bachelors": true,
        "Masters": true,
        "Doctorate": false,
        "Other": false
    },{
    "MajorName": "Psychology (AS)",
        "Bachelors": true,
        "Masters": true,
        "Doctorate": true,
        "Other": false
    },{
    "MajorName": "Public Administration (AS)",
        "Bachelors": false,
        "Masters": true,
        "Doctorate": false,
        "Other": true
    },{
    "MajorName": "Rangeland Ecology and Watershed Management (AG)",
        "Bachelors": true,
        "Masters": true,
        "Doctorate": true,
        "Other": false
    },{
    "MajorName": "Rangeland Ecology and Watershed Management/Water Resources (AG)",
        "Bachelors": false,
        "Masters": true,
        "Doctorate": false,
        "Other": false
    },{
    "MajorName": "Religious Studies (AS)",
        "Bachelors": true,
        "Masters": false,
        "Doctorate": false,
        "Other": false
    },{
    "MajorName": "Reproductive Biology (AG and AS)",
        "Bachelors": false,
        "Masters": true,
        "Doctorate": true,
        "Other": false
    },{
    "MajorName": "Secondary Education (ED)",
        "Bachelors": true,
        "Masters": false,
        "Doctorate": false,
        "Other": false
    },{
    "MajorName": "Social Science (AS)",
        "Bachelors": true,
        "Masters": false,
        "Doctorate": false,
        "Other": false
    },{
    "MajorName": "Social Work (HS)",
        "Bachelors": true,
        "Masters": true,
        "Doctorate": false,
        "Other": false
    },{
    "MajorName": "Sociology (AS)",
        "Bachelors": true,
        "Masters": true,
        "Doctorate": false,
        "Other": false
    },{
    "MajorName": "Soil Science (AG)",
        "Bachelors": false,
        "Masters": true,
        "Doctorate": true,
        "Other": false
    },{
    "MajorName": "Soil Science/Water Resources (AG)",
        "Bachelors": false,
        "Masters": true,
        "Doctorate": false,
        "Other": false
    },{
    "MajorName": "Spanish (AS)",
        "Bachelors": true,
        "Masters": true,
        "Doctorate": false,
        "Other": false
    },{
    "MajorName": "Speech, Language and Hearing Sciences (HS)",
        "Bachelors": true,
        "Masters": false,
        "Doctorate": false,
        "Other": false
    },{
    "MajorName": "Speech-Language Pathology (HS)",
        "Bachelors": false,
        "Masters": true,
        "Doctorate": false,
        "Other": false
    },{
    "MajorName": "Statistics (AS)",
        "Bachelors": true,
        "Masters": true,
        "Doctorate": true,
        "Other": false
    },{
    "MajorName": "Theatre and Dance (AS)",
        "Bachelors": true,
        "Masters": false,
        "Doctorate": false,
        "Other": false
    },{
    "MajorName": "Theatre and Dance-Professional (AS)",
        "Bachelors": true,
        "Masters": false,
        "Doctorate": false,
        "Other": false
    },{
    "MajorName": "Wildlife and Fisheries Biology and Management - Professional (AS)",
        "Bachelors": true,
        "Masters": false,
        "Doctorate": false,
        "Other": false
    },{
    "MajorName": "Zoology and Physiology (AS)",
        "Bachelors": false,
        "Masters": true,
        "Doctorate": true,
        "Other": false
    },{
    "MajorName": "Zoology and Physiology/Water Resources (AS)",
        "Bachelors": false,
        "Masters": true,
        "Doctorate": false,
        "Other": false
    },{
    "MajorName": "Zoology (AS)",
        "Bachelors": true,
        "Masters": false,
        "Doctorate": false,
        "Other": false
    }
]